{
  "schemaVersion": "trust-gradient-auto-apply-v1",
  "proposalRef": "proposal/scene-only-color-tweak",
  "tier": "low",
  "eligibility": "auto-apply-eligible",
  "confidence": 0.96,
  "rerunGates": {
    "mechanical": "pass",
    "runtime": "pass",
    "visual": "pass",
    "semantic": "pass"
  },
  "budget": {
    "remaining": 3,
    "cost": 1
  },
  "autonomyEnabled": true,
  "rollbackHandle": {
    "applyTransactionId": "txn-scene-001",
    "reverseRef": "examples/trust-gradient-v1/fixtures/reverse/txn-scene-001.json"
  }
}
